[{"title": "OpEd: White People, It\u2019s Time to Use Your Privilege, Whether You Believe You Have It or Not", "sentiment": {"Libertarian": 0.2074291855, "Liberal": 0.2155700475, "Green": 0.3752526641, "Conservative": 0.2017480582}, "subreddit": "politics"}, {"title": "NASCAR owners side with Trump, take firm stance against anthem protests", "sentiment": {"Libertarian": 0.2185945511, "Green": 0.056407004600000005, "Liberal": 0.6193922758, "Conservative": 0.10560621320000001}, "subreddit": "politics"}, {"title": "NASCAR fans: Confederate flag still important symbol", "sentiment": {"Libertarian": 0.1678523272, "Liberal": 0.28442060950000003, "Green": 0.29686576130000003, "Conservative": 0.2508613765}, "subreddit": "politics"}, {"title": "What Happened reveals Hillary Clinton as a smart thinker \u2013 unlike the man who beat her", "sentiment": {"Libertarian": 0.2145979851, "Liberal": 0.0175361764, "Green": 0.0451136045, "Conservative": 0.7227523327}, "subreddit": "politics"}, {"title": "Trump 'Kneel' Attack Gives His Base Reason to Stand - NBC News", "sentiment": {"Libertarian": 0.2081752717, "Liberal": 0.213585943, "Green": 0.3663488925, "Conservative": 0.2118899226}, "subreddit": "politics"}, {"title": "Supreme Court drops Trump travel ban from oral argument calendar", "sentiment": {"Libertarian": 0.5020292997, "Green": 0.16796880960000002, "Liberal": 0.2257524729, "Conservative": 0.10424938800000001}, "subreddit": "politics"}, {"title": "Tony Blair Says Bernie Doesn't Have the Answers (Public Opinion Says Otherwise)", "sentiment": {"Libertarian": 0.1829625815, "Liberal": 0.2131322473, "Green": 0.4204076827, "Conservative": 0.1834975034}, "subreddit": "politics"}, {"title": "He is in prison for life for a violent carjacking. His mother says he belongs in a mental hospital.", "sentiment": {"Libertarian": 0.5256791711000001, "Green": 0.0727331564, "Liberal": 0.1154556796, "Conservative": 0.286131978}, "subreddit": "politics"}, {"title": "Former U.S. Rep. Anthony Weiner sentenced to 21 months in sexting case that rocked presidential race", "sentiment": {"Libertarian": 0.44398626690000004, "Liberal": 0.0546523109, "Green": 0.06343729790000001, "Conservative": 0.4379241467}, "subreddit": "politics"}, {"title": "I Understand Why They Knelt", "sentiment": {"Libertarian": 0.2201740593, "Liberal": 0.2271648943, "Green": 0.336881727, "Conservative": 0.21577937900000002}, "subreddit": "politics"}, {"title": "Alejandro Villanueva only Steelers player to appear for national anthem", "sentiment": {"Libertarian": 0.2733657658, "Liberal": 0.23375284670000002, "Green": 0.29204243420000003, "Conservative": 0.2008389831}, "subreddit": "politics"}, {"title": "Valerie Plame resigns from Ploughshares Fund after tweeting anti-Semitic article", "sentiment": {"Libertarian": 0.1830077171, "Liberal": 0.2711213529, "Green": 0.3646389246, "Conservative": 0.1812320054}, "subreddit": "politics"}, {"title": "Trump claims he doesn't know much about 'Ray' Moore", "sentiment": {"Libertarian": 0.2173778564, "Liberal": 0.2062375247, "Green": 0.3298270702, "Conservative": 0.24655756350000002}, "subreddit": "politics"}, {"title": "As GOP\u2019s repeal bill struggles, Democrats ask whether they gave it life", "sentiment": {"Libertarian": 0.1720498204, "Green": 0.2303398401, "Liberal": 0.4747277796, "Conservative": 0.122882612}, "subreddit": "politics"}, {"title": "Trump Says His Criticism Of NFL Has \u2018Nothing\u2019 To Do With Race", "sentiment": {"Libertarian": 0.2201740593, "Liberal": 0.2271648943, "Green": 0.336881727, "Conservative": 0.21577937900000002}, "subreddit": "politics"}, {"title": "Trump continues NFL clash: NASCAR fans won't disrespect our country", "sentiment": {"Libertarian": 0.15124124290000002, "Liberal": 0.20302610100000001, "Green": 0.3657859862, "Conservative": 0.2799467444}, "subreddit": "politics"}, {"title": "NASCAR owners say they wouldn\u2019t tolerate national anthem protests at races", "sentiment": {"Libertarian": 0.3672356308, "Green": 0.0276494753, "Liberal": 0.3988599181, "Conservative": 0.2062549442}, "subreddit": "politics"}, {"title": "Trump thanks NASCAR and booing NFL fans", "sentiment": {"Libertarian": 0.2075697035, "Liberal": 0.2259342819, "Green": 0.36685985330000004, "Conservative": 0.1996361017}, "subreddit": "politics"}, {"title": "Former U.S. Rep. Anthony Weiner sentenced to 21 months in sexting case that rocked presidential race", "sentiment": {"Libertarian": 0.44398626690000004, "Liberal": 0.0546523109, "Green": 0.06343729790000001, "Conservative": 0.4379241467}, "subreddit": "politics"}, {"title": "Trump responds to NFL protests: 'Standing with locked arms is good, kneeling is not acceptable'", "sentiment": {"Libertarian": 0.33459660410000003, "Liberal": 0.1638016403, "Green": 0.26638996600000003, "Conservative": 0.2352118045}, "subreddit": "politics"}, {"title": "Weiner faces sentencing in latest chapter of sexting drama", "sentiment": {"Libertarian": 0.4490297139, "Green": 0.1052358598, "Liberal": 0.2899786532, "Conservative": 0.1557557434}, "subreddit": "politics"}, {"title": "Luther Strange warns Roy Moore would be Todd Akin-like anchor on GOP", "sentiment": {"Libertarian": 0.20852224530000002, "Liberal": 0.1577348858, "Green": 0.2101363242, "Conservative": 0.4236065745}, "subreddit": "politics"}, {"title": "White House announces new tech jobs initiative", "sentiment": {"Libertarian": 0.1938329339, "Liberal": 0.2097132951, "Green": 0.44207873940000003, "Conservative": 0.154374972}, "subreddit": "politics"}, {"title": "Anthony Weiner being sentenced in sexting case that played a role in presidential election", "sentiment": {"Libertarian": 0.3934421837, "Green": 0.1329650581, "Liberal": 0.22506177430000002, "Conservative": 0.2485309243}, "subreddit": "politics"}, {"title": "Cut Off From The World, Puerto Ricans Search For A Ghost Of A Signal", "sentiment": {"Libertarian": 0.21469034250000002, "Liberal": 0.22133843600000003, "Green": 0.3571846187, "Conservative": 0.2067866176}, "subreddit": "technology"}, {"title": "Self-Driving Cars Will Kill People. Who Decides Who Dies? | WIRED", "sentiment": {"Libertarian": 0.2249744534, "Liberal": 0.2089590728, "Green": 0.3618192971, "Conservative": 0.2042472363}, "subreddit": "technology"}, {"title": "Putin Weighs in on Artificial Intelligence and Elon Musk Is Alarmed", "sentiment": {"Libertarian": 0.19781932230000002, "Liberal": 0.2144400477, "Green": 0.3998472691, "Conservative": 0.1878933012}, "subreddit": "technology"}, {"title": "Artificial intelligence could make brands obsolete", "sentiment": {"Libertarian": 0.2629882991, "Liberal": 0.1214826033, "Green": 0.48960796, "Conservative": 0.12592116}, "subreddit": "technology"}, {"title": "Microsoft makes play for next wave of computing with quantum computing toolkit", "sentiment": {"Libertarian": 0.2281034738, "Liberal": 0.1514758617, "Green": 0.5420925021, "Conservative": 0.07832819220000001}, "subreddit": "technology"}, {"title": "Wind Energy Used To Mine Cryptocurrency To Fund Climate Research", "sentiment": {"Libertarian": 0.2201740593, "Liberal": 0.2271648943, "Green": 0.336881727, "Conservative": 0.21577937900000002}, "subreddit": "technology"}, {"title": "Obama tried to give Zuckerberg a wake-up call over fake news on Facebook", "sentiment": {"Libertarian": 0.2823495567, "Liberal": 0.1968633085, "Green": 0.3268001378, "Conservative": 0.1939870119}, "subreddit": "technology"}, {"title": "Intel Core i9-7980XE And Core i9-7960X Review: Intel Attacks AMD Threadripper", "sentiment": {"Libertarian": 0.2116420418, "Liberal": 0.2213464081, "Green": 0.3584333062, "Conservative": 0.208578214}, "subreddit": "technology"}, {"title": "Intel unveils their 8th-generation Coffee Lake desktop processors", "sentiment": {"Libertarian": 0.20884826780000001, "Liberal": 0.2313688844, "Green": 0.4039083719, "Conservative": 0.15587450560000002}, "subreddit": "technology"}, {"title": "Got a tech question or want to discuss tech? Weekly /r/Technology Tech Support / General Discussion Thread", "sentiment": {"Libertarian": 0.8202840686, "Liberal": 0.0556235723, "Green": 0.0641441047, "Conservative": 0.059948250700000004}, "subreddit": "technology"}, {"title": "Send nudes: Ransomware demands x-rated photos to unlock victim's device", "sentiment": {"Libertarian": 0.25557789210000004, "Liberal": 0.1150166839, "Green": 0.3693176508, "Conservative": 0.2600878179}, "subreddit": "technology"}, {"title": "Intel launches 8th-gen Core desktop chips, claims the Core i7-8700K is its best gaming chip ever", "sentiment": {"Libertarian": 0.32465532420000004, "Liberal": 0.2192192078, "Green": 0.3081358969, "Conservative": 0.1479895562}, "subreddit": "technology"}, {"title": "Amazon's Alexa is making waves", "sentiment": {"Libertarian": 0.1786630303, "Liberal": 0.2165575773, "Green": 0.42977562550000004, "Conservative": 0.1750038266}, "subreddit": "technology"}, {"title": "Why You Shouldn't Charge Your Mobile Phone Overnight", "sentiment": {"Libertarian": 0.19764746730000002, "Liberal": 0.20948489010000002, "Green": 0.3947067261, "Conservative": 0.1981609464}, "subreddit": "technology"}, {"title": "Michael Bloomberg's Dystopian Digital Future [Interview Comnentary]", "sentiment": {"Libertarian": 0.19215388600000002, "Liberal": 0.2070411742, "Green": 0.4123055041, "Conservative": 0.1884993911}, "subreddit": "technology"}, {"title": "meet the world's top 50 innovators in a few days in London", "sentiment": {"Libertarian": 0.2353628278, "Liberal": 0.1410249174, "Green": 0.4591683447, "Conservative": 0.16444392500000002}, "subreddit": "technology"}, {"title": "What's it like to do a space walk? Come and ask NASA", "sentiment": {"Libertarian": 0.2401573062, "Liberal": 0.17672671380000002, "Green": 0.4172249436, "Conservative": 0.1658910066}, "subreddit": "technology"}, {"title": "New Galaxy X Leaks Point To Launch Date For Samsung's Folding Phone", "sentiment": {"Libertarian": 0.1975604743, "Liberal": 0.21421596410000002, "Green": 0.4025972188, "Conservative": 0.1856263876}, "subreddit": "technology"}, {"title": "Yubico's new authentication key is super tiny and works with USB-C ports", "sentiment": {"Libertarian": 0.2038448155, "Liberal": 0.2044988275, "Green": 0.5099233985, "Conservative": 0.0817329735}, "subreddit": "technology"}, {"title": "Facebook can't hide behind algorithms", "sentiment": {"Libertarian": 0.4334498942, "Green": 0.1243159845, "Liberal": 0.145636797, "Conservative": 0.2965972722}, "subreddit": "technology"}, {"title": "The Impossible Burger: The Science Inside the Meat-Free Burger That Bleeds", "sentiment": {"Libertarian": 0.2037512809, "Liberal": 0.2235237807, "Green": 0.3678952157, "Conservative": 0.2048297822}, "subreddit": "technology"}, {"title": "Russian hackers exploited a Google flaw the company has refused to fix: Hacker team \u201cFancy Bear\u201d used a Google security flaw to attack journalists, and the tech giant has done nothing", "sentiment": {"Libertarian": 0.2531768084, "Green": 0.1533783227, "Liberal": 0.2996222973, "Conservative": 0.29382258650000004}, "subreddit": "technology"}, {"title": "Intel launches 8th-gen Core desktop chips, claims new Core i7-8700K is its best gaming chip ever", "sentiment": {"Libertarian": 0.33126869800000003, "Liberal": 0.22062148150000002, "Green": 0.30096432570000003, "Conservative": 0.1471454948}, "subreddit": "technology"}, {"title": "As devices become increasingly connected, they start expressing unique identities that interlace with those of their owners.", "sentiment": {"Libertarian": 0.4937731326, "Green": 0.1550184935, "Liberal": 0.1722555757, "Conservative": 0.178952828}, "subreddit": "technology"}, {"title": "The case for Apple to finally just make a TV", "sentiment": {"Libertarian": 0.2286681533, "Liberal": 0.2060724199, "Green": 0.3726872802, "Conservative": 0.1925721765}, "subreddit": "technology"}, {"title": "Macron wants make wolf whistling and asking women for their phone number illegal under new plans to end 'macho' culture in France", "sentiment": {"Libertarian": 0.0906639919, "Green": 0.248059094, "Liberal": 0.5748370886, "Conservative": 0.0864398032}, "subreddit": "worldnews"}, {"title": "North Korea 'has right to shoot down US bombers' after Donald Trump 'declared war'", "sentiment": {"Libertarian": 0.3400205076, "Green": 0.2117420882, "Liberal": 0.27597248550000003, "Conservative": 0.172264874}, "subreddit": "worldnews"}, {"title": "Kurds rally for independence ahead of referendum in Iraqi Kurdistan", "sentiment": {"Libertarian": 0.3126826286, "Green": 0.17683158810000002, "Liberal": 0.1910443306, "Conservative": 0.3194414675}, "subreddit": "worldnews"}, {"title": "North Korea's Foreign Minister Accuses Trump of Declaring War", "sentiment": {"Libertarian": 0.1959116906, "Liberal": 0.2126295716, "Green": 0.40589302780000003, "Conservative": 0.18556572500000001}, "subreddit": "worldnews"}, {"title": "New Order Bars Almost All Travel From Seven Countries", "sentiment": {"Libertarian": 0.2201740593, "Liberal": 0.2271648943, "Green": 0.336881727, "Conservative": 0.21577937900000002}, "subreddit": "worldnews"}, {"title": "Massive drills held on Iraq border ahead of Kurdistan independence referendum", "sentiment": {"Libertarian": 0.2293629348, "Liberal": 0.18622063100000003, "Green": 0.3180881143, "Conservative": 0.2663282752}, "subreddit": "worldnews"}, {"title": "N. Korea has right to shoot down strategic US bombers even not in our airspace - foreign minister", "sentiment": {"Libertarian": 0.2516709864, "Green": 0.1257390529, "Liberal": 0.1783193499, "Conservative": 0.44427058100000005}, "subreddit": "worldnews"}, {"title": "Fitch upgrades Russia\u2019s credit rating from stable to positive", "sentiment": {"Libertarian": 0.2069894075, "Liberal": 0.1971835941, "Green": 0.43156200650000004, "Conservative": 0.164264977}, "subreddit": "worldnews"}, {"title": "North Korean foreign minister says Pyongyang reserves right to shoot down US bombers in international air space as Donald Trump's latest comments are 'clearly a declaration of war'", "sentiment": {"Libertarian": 0.5735519528, "Green": 0.0867632478, "Liberal": 0.2055321485, "Conservative": 0.1341526955}, "subreddit": "worldnews"}, {"title": "\u2018No proper precautions\u2019: US-led coalition airstrikes near Raqqa killed 84 civilians, HRW says", "sentiment": {"Libertarian": 0.11802412570000001, "Liberal": 0.2523500621, "Green": 0.5598465204, "Conservative": 0.0697792768}, "subreddit": "worldnews"}, {"title": "North Korea's foreign minister says Trump has declared war on country", "sentiment": {"Libertarian": 0.4284506738, "Liberal": 0.1891037226, "Green": 0.1979793906, "Conservative": 0.1844661832}, "subreddit": "worldnews"}, {"title": "Dubai jumpstarts e-cars' sales: Free Salik tags, charging, parking", "sentiment": {"Libertarian": 0.1194062904, "Liberal": 0.0287990887, "Green": 0.7913401723, "Conservative": 0.060454443100000005}, "subreddit": "worldnews"}, {"title": "North Korean minister says Trump has declared 'war'", "sentiment": {"Libertarian": 0.3776183128, "Green": 0.1995639652, "Liberal": 0.2906327844, "Conservative": 0.132184878}, "subreddit": "worldnews"}, {"title": "For help fighting terror, London police look to Israel", "sentiment": {"Libertarian": 0.272513926, "Liberal": 0.20798543100000003, "Green": 0.2607217431, "Conservative": 0.2587789297}, "subreddit": "worldnews"}, {"title": "No intervention: Venezuela has right to pursue own path, Ecuador president tells RT", "sentiment": {"Libertarian": 0.3078337908, "Liberal": 0.18432435390000002, "Green": 0.2662168145, "Conservative": 0.24162510040000001}, "subreddit": "worldnews"}, {"title": "Presidential Proclamation Enhancing Vetting Capabilities and Processes for Detecting Attempted Entry Into the United States by Terrorists or Other Public-Safety Threats", "sentiment": {"Libertarian": 0.20756940540000002, "Liberal": 0.2191324979, "Green": 0.3676536083, "Conservative": 0.2056445777}, "subreddit": "worldnews"}, {"title": "Tehran could \u2018walk away\u2019 from nuclear deal \u2013 Iran\u2019s FM", "sentiment": {"Libertarian": 0.1026802361, "Liberal": 0.1449164748, "Green": 0.6266896725000001, "Conservative": 0.12571364640000002}, "subreddit": "worldnews"}, {"title": "North Korea says Trump declared war", "sentiment": {"Libertarian": 0.2565895617, "Liberal": 0.2188923657, "Green": 0.3322457373, "Conservative": 0.1922723204}, "subreddit": "worldnews"}, {"title": "Iran and Turkey move troops and equipment to Iraqi Borders as Kurds vote to form a new independent country", "sentiment": {"Libertarian": 0.22931097450000001, "Liberal": 0.15425646310000002, "Green": 0.5226196051, "Conservative": 0.0938130766}, "subreddit": "worldnews"}, {"title": "Jews around world concerned by far-right breakthrough in German election", "sentiment": {"Libertarian": 0.15910209720000001, "Liberal": 0.2431245297, "Green": 0.41724550720000003, "Conservative": 0.1805278659}, "subreddit": "worldnews"}, {"title": "Palestinian unity government to meet in Gaza next week - statement", "sentiment": {"Libertarian": 0.25302821400000003, "Green": 0.2536718249, "Liberal": 0.33098667860000003, "Conservative": 0.16231320800000001}, "subreddit": "worldnews"}, {"title": "The Latest: AfD leader refuses to join parliamentary group", "sentiment": {"Libertarian": 0.14218290150000001, "Green": 0.304002732, "Liberal": 0.4491863847, "Conservative": 0.10462798920000001}, "subreddit": "worldnews"}, {"title": "Uber\u2019s new CEO has apologized to London in an open letter", "sentiment": {"Libertarian": 0.2169385403, "Liberal": 0.2530574501, "Green": 0.3280118704, "Conservative": 0.2019921988}, "subreddit": "worldnews"}, {"title": "Man arrested after clinging to fast-moving train in Australia", "sentiment": {"Libertarian": 0.17185030880000002, "Liberal": 0.19150468710000002, "Green": 0.3781919181, "Conservative": 0.2584530711}, "subreddit": "worldnews"}, {"title": "North Korea accuses Trump of making declaration of war", "sentiment": {"Libertarian": 0.40208825470000004, "Green": 0.1868339628, "Liberal": 0.2498404384, "Conservative": 0.1612372845}, "subreddit": "worldnews"}, {"title": "Steelers player who stood for national anthem has top-selling jersey", "sentiment": {"Libertarian": 0.2178035975, "Green": 0.1104770452, "Liberal": 0.3981563449, "Conservative": 0.2735630274}, "subreddit": "news"}, {"title": "Upstate restaurant owner to stop showing NFL games in response to kneeling players", "sentiment": {"Libertarian": 0.3236918151, "Liberal": 0.1976877749, "Green": 0.32041874530000003, "Conservative": 0.1582016647}, "subreddit": "news"}, {"title": "Man quits NFL stadium job after National Anthem protests", "sentiment": {"Libertarian": 0.2044608742, "Liberal": 0.224221468, "Green": 0.38642409440000003, "Conservative": 0.1848935038}, "subreddit": "news"}, {"title": "Violent crime rising throughout US, FBI says", "sentiment": {"Libertarian": 0.2238597125, "Liberal": 0.1934595108, "Green": 0.3744742274, "Conservative": 0.2082064897}, "subreddit": "news"}, {"title": "University 'turned down politically incorrect transgender research'", "sentiment": {"Libertarian": 0.024239542000000003, "Green": 0.0023321796, "Liberal": 0.0443411581, "Conservative": 0.9290870428}, "subreddit": "news"}, {"title": "North Korea blows up US aircraft carrier in new propaganda video", "sentiment": {"Libertarian": 0.4251255095, "Green": 0.1042810455, "Liberal": 0.29935964940000004, "Conservative": 0.1712338179}, "subreddit": "news"}, {"title": "Cincinnati Zoo welcomes new gorilla a year after Harambe", "sentiment": {"Libertarian": 0.0705449283, "Liberal": 0.0967485085, "Green": 0.7748705149, "Conservative": 0.0578360148}, "subreddit": "news"}, {"title": "Mystery of Great Pyramid may be solved, researchers say", "sentiment": {"Libertarian": 0.1985757947, "Liberal": 0.2618807852, "Green": 0.4233523905, "Conservative": 0.1161910594}, "subreddit": "news"}, {"title": "Hotel refuses to rent rooms to Pakistan International Airlines' crew", "sentiment": {"Libertarian": 0.2879239917, "Liberal": 0.2109552473, "Green": 0.2633969486, "Conservative": 0.23772384230000002}, "subreddit": "news"}, {"title": "Singer of national anthem at Seahawks-Titans game takes a knee", "sentiment": {"Libertarian": 0.23329199850000001, "Liberal": 0.2922655344, "Green": 0.3030861616, "Conservative": 0.1713563502}, "subreddit": "news"}, {"title": "Detroit man charged with raping woman on Michigan State campus", "sentiment": {"Libertarian": 0.3060305417, "Green": 0.076366052, "Liberal": 0.1004451662, "Conservative": 0.5171582103}, "subreddit": "news"}, {"title": "\u2018Goodbye Pittsburgh Steelers, Burn In Hell\u2019: Angry Fans Burn Gear Over National Anthem Protest-CBS", "sentiment": {"Libertarian": 0.21342431010000001, "Liberal": 0.2175709009, "Green": 0.35869586470000003, "Conservative": 0.2103089243}, "subreddit": "news"}, {"title": "Reports of Confederate flag display, racial slurs during football game puts Colorado schools at odds", "sentiment": {"Libertarian": 0.0489616506, "Green": 0.0089313602, "Liberal": 0.0956369787, "Conservative": 0.8464700580000001}, "subreddit": "news"}, {"title": "Man attacked from behind and stabbed in the neck as he arrived at a mosque for evening prayers", "sentiment": {"Libertarian": 0.0803775713, "Green": 0.0662112683, "Liberal": 0.3482682407, "Conservative": 0.5051429272}, "subreddit": "news"}, {"title": "Morgan Freeman Angers Russians Over Video About 2016 Election", "sentiment": {"Libertarian": 0.20792934300000002, "Liberal": 0.2201665491, "Green": 0.3605802059, "Conservative": 0.21132384240000002}, "subreddit": "news"}, {"title": "Men rescued from scafell pike due to being \"unable to walk from cannabis use\"", "sentiment": {"Libertarian": 0.731707871, "Green": 0.0824303403, "Liberal": 0.11106491090000001, "Conservative": 0.0747968853}, "subreddit": "news"}, {"title": "Walt Disney threatens to pull ESPN, ABC from Optimum", "sentiment": {"Libertarian": 0.18918529150000002, "Liberal": 0.1927734315, "Green": 0.4314590394, "Conservative": 0.1865822524}, "subreddit": "news"}, {"title": "Turkey extends troop deployment mandate, pressures Iraqi Kurds on vote", "sentiment": {"Libertarian": 0.3251449764, "Liberal": 0.1383526921, "Green": 0.3460859954, "Conservative": 0.1904164106}, "subreddit": "news"}, {"title": "Little Rock School Integration Anniversary", "sentiment": {"Libertarian": 0.2201740593, "Liberal": 0.2271648943, "Green": 0.336881727, "Conservative": 0.21577937900000002}, "subreddit": "news"}, {"title": "Angela Merkel Wins Mandate For 4th Term", "sentiment": {"Libertarian": 0.2146681547, "Liberal": 0.2161762416, "Green": 0.3601463139, "Conservative": 0.2090092748}, "subreddit": "news"}, {"title": "Silicon Valley's men are embracing 'men's rights' as pushback against gender equality movement", "sentiment": {"Libertarian": 0.1683861315, "Green": 0.0029552951, "Liberal": 0.4359268248, "Conservative": 0.3927317858}, "subreddit": "news"}, {"title": "Aussies \u2018treated like criminals\u2019 at US border", "sentiment": {"Libertarian": 0.201347366, "Liberal": 0.21768583360000002, "Green": 0.3782891929, "Conservative": 0.2026776224}, "subreddit": "news"}, {"title": "U.S.-backed alliance says Russian jets struck its fighters in east Syria", "sentiment": {"Libertarian": 0.19408240910000002, "Green": 0.2473536432, "Liberal": 0.3375781178, "Conservative": 0.22098574040000002}, "subreddit": "news"}, {"title": "Civilian deaths are 'price you pay' to beat Isis, says British general in Iraq", "sentiment": {"Libertarian": 0.2995826602, "Green": 0.23783108590000002, "Liberal": 0.2770424783, "Conservative": 0.18554377560000002}, "subreddit": "news"}]