[{"sentiment_compound": 0.4019, "id": "73ry6i"}, {"sentiment_compound": 0.0, "id": "73sfzt"}, {"sentiment_compound": 0.3182, "id": "73q43v"}, {"sentiment_compound": -0.34, "id": "73qsn8"}, {"sentiment_compound": -0.5423, "id": "73snpa"}, {"sentiment_compound": -0.5709, "id": "73sltg"}, {"sentiment_compound": -0.5233, "id": "73rtew"}, {"sentiment_compound": 0.0, "id": "73rlv1"}, {"sentiment_compound": 0.0772, "id": "73qtsn"}, {"sentiment_compound": -0.5267, "id": "73qn7u"}, {"sentiment_compound": 0.0, "id": "73ssp8"}, {"sentiment_compound": 0.0, "id": "73q8qa"}, {"sentiment_compound": 0.4588, "id": "73rqtv"}, {"sentiment_compound": 0.3182, "id": "73toei"}, {"sentiment_compound": 0.0, "id": "73qa2w"}, {"sentiment_compound": -0.4215, "id": "73t23z"}, {"sentiment_compound": 0.296, "id": "73rpie"}, {"sentiment_compound": 0.6369, "id": "73pmtq"}, {"sentiment_compound": -0.2732, "id": "73ru1x"}, {"sentiment_compound": 0.5574, "id": "73tl9n"}, {"sentiment_compound": 0.3477, "id": "73q035"}, {"sentiment_compound": 0.6369, "id": "73qwzt"}, {"sentiment_compound": 0.0, "id": "73u3xt"}, {"sentiment_compound": 0.6369, "id": "73pdcz"}, {"sentiment_compound": -0.4767, "id": "73r3xs"}, {"sentiment_compound": 0.3612, "id": "73q2um"}, {"sentiment_compound": 0.0, "id": "73rvk2"}, {"sentiment_compound": -0.2023, "id": "73qg56"}, {"sentiment_compound": 0.7089, "id": "73t5hf"}, {"sentiment_compound": 0.2732, "id": "73tf1a"}, {"sentiment_compound": 0.3182, "id": "73pzbe"}, {"sentiment_compound": 0.0, "id": "73pvyp"}, {"sentiment_compound": 0.0, "id": "73v4jg"}, {"sentiment_compound": 0.0, "id": "73su61"}, {"sentiment_compound": 0.0, "id": "73pe1l"}, {"sentiment_compound": -0.0772, "id": "73snip"}, {"sentiment_compound": -0.5574, "id": "73rn4f"}, {"sentiment_compound": 0.3527, "id": "73ur1f"}, {"sentiment_compound": 0.0, "id": "73tkhc"}, {"sentiment_compound": 0.0, "id": "73re86"}, {"sentiment_compound": 0.0, "id": "73sjuo"}, {"sentiment_compound": 0.0, "id": "73s2g6"}, {"sentiment_compound": 0.0, "id": "73v6vb"}, {"sentiment_compound": -0.1027, "id": "73sk2b"}, {"sentiment_compound": -0.34, "id": "73qdzo"}, {"sentiment_compound": 0.0, "id": "73snpc"}, {"sentiment_compound": 0.6908, "id": "73sivg"}, {"sentiment_compound": 0.0, "id": "73r4x6"}, {"sentiment_compound": 0.0, "id": "73r2jc"}, {"sentiment_compound": 0.0, "id": "73r410"}, {"sentiment_compound": -0.3182, "id": "73rtsv"}, {"sentiment_compound": 0.0, "id": "73uym3"}, {"sentiment_compound": -0.8442, "id": "73titg"}, {"sentiment_compound": -0.34, "id": "73sjh5"}, {"sentiment_compound": 0.0772, "id": "73tmkh"}, {"sentiment_compound": 0.4019, "id": "73s72e"}, {"sentiment_compound": -0.6369, "id": "73sqzq"}, {"sentiment_compound": -0.0772, "id": "73u3lo"}, {"sentiment_compound": 0.4939, "id": "73te4f"}, {"sentiment_compound": -0.5423, "id": "73t2g1"}, {"sentiment_compound": 0.0, "id": "73pxix"}, {"sentiment_compound": -0.4939, "id": "73taz8"}, {"sentiment_compound": -0.4767, "id": "73su2m"}, {"sentiment_compound": 0.0397, "id": "73vbh1"}, {"sentiment_compound": 0.0, "id": "73sevj"}, {"sentiment_compound": -0.0772, "id": "73uhlr"}, {"sentiment_compound": 0.7003, "id": "73u3xj"}, {"sentiment_compound": 0.0, "id": "73ubnx"}, {"sentiment_compound": -0.6486, "id": "73t5vb"}, {"sentiment_compound": -0.296, "id": "73rta8"}, {"sentiment_compound": -0.128, "id": "73ptta"}, {"sentiment_compound": -0.7579, "id": "73tx9t"}, {"sentiment_compound": -0.2263, "id": "73um0q"}, {"sentiment_compound": -0.6249, "id": "73scr7"}, {"sentiment_compound": -0.2263, "id": "73u0y8"}, {"sentiment_compound": 0.0, "id": "73rktn"}, {"sentiment_compound": 0.4019, "id": "73sarg"}, {"sentiment_compound": 0.0, "id": "73snpq"}, {"sentiment_compound": 0.4019, "id": "73rtos"}, {"sentiment_compound": 0.1877, "id": "73w7un"}, {"sentiment_compound": 0.5707, "id": "73pd9s"}, {"sentiment_compound": 0.0, "id": "73uxt0"}, {"sentiment_compound": 0.5574, "id": "73ujdb"}, {"sentiment_compound": 0.8173, "id": "73rwv5"}, {"sentiment_compound": 0.0, "id": "73t91z"}, {"sentiment_compound": -0.34, "id": "73u1dn"}, {"sentiment_compound": 0.5859, "id": "73s9b9"}, {"sentiment_compound": -0.1779, "id": "73sobq"}, {"sentiment_compound": 0.0, "id": "73tv2b"}, {"sentiment_compound": 0.0, "id": "73s822"}, {"sentiment_compound": -0.5859, "id": "73rkz7"}, {"sentiment_compound": -0.296, "id": "73tmad"}, {"sentiment_compound": -0.34, "id": "73s44w"}, {"sentiment_compound": 0.0, "id": "73rgd0"}, {"sentiment_compound": 0.0, "id": "73vdb0"}, {"sentiment_compound": 0.0, "id": "73s1v8"}, {"sentiment_compound": 0.2732, "id": "73ttei"}, {"sentiment_compound": -0.3818, "id": "73tlat"}, {"sentiment_compound": 0.0772, "id": "73w74o"}, {"sentiment_compound": -0.2263, "id": "73w5vp"}, {"sentiment_compound": 0.0, "id": "73rmxg"}, {"sentiment_compound": -0.8074, "id": "73rukc"}, {"sentiment_compound": 0.0, "id": "73r59t"}, {"sentiment_compound": -0.5423, "id": "73r89v"}, {"sentiment_compound": 0.0, "id": "73qcql"}, {"sentiment_compound": 0.0, "id": "73r8ob"}, {"sentiment_compound": 0.5859, "id": "73te3b"}, {"sentiment_compound": 0.5106, "id": "73ry4k"}, {"sentiment_compound": 0.8519, "id": "73uapa"}, {"sentiment_compound": -0.6808, "id": "73t8kv"}, {"sentiment_compound": 0.0, "id": "73ru7e"}, {"sentiment_compound": -0.5106, "id": "73u452"}, {"sentiment_compound": -0.5574, "id": "73s521"}, {"sentiment_compound": 0.0, "id": "73ren2"}, {"sentiment_compound": 0.0, "id": "73tf70"}, {"sentiment_compound": 0.6705, "id": "73t8hr"}, {"sentiment_compound": 0.8779, "id": "73t1ex"}, {"sentiment_compound": 0.2235, "id": "73tuux"}, {"sentiment_compound": 0.4767, "id": "73pm1o"}, {"sentiment_compound": 0.0, "id": "73v2dr"}, {"sentiment_compound": 0.0, "id": "73sw8w"}, {"sentiment_compound": 0.0, "id": "73qpla"}, {"sentiment_compound": 0.4019, "id": "73uwwk"}, {"sentiment_compound": 0.0, "id": "73ut1t"}, {"sentiment_compound": 0.2484, "id": "73vlha"}, {"sentiment_compound": -0.8225, "id": "73pvyt"}, {"sentiment_compound": 0.7717, "id": "73sn2b"}, {"sentiment_compound": 0.2952, "id": "73pz8g"}, {"sentiment_compound": 0.0, "id": "73toda"}, {"sentiment_compound": 0.0, "id": "73waq6"}, {"sentiment_compound": 0.0, "id": "73vvhu"}, {"sentiment_compound": -0.1531, "id": "73v6h7"}, {"sentiment_compound": 0.0, "id": "73u4wv"}, {"sentiment_compound": 0.0, "id": "73tusa"}, {"sentiment_compound": 0.0, "id": "73piko"}, {"sentiment_compound": -0.4019, "id": "73q8dg"}, {"sentiment_compound": -0.7269, "id": "73wjyt"}, {"sentiment_compound": -0.3804, "id": "73wdls"}, {"sentiment_compound": 0.0, "id": "73vqzi"}, {"sentiment_compound": -0.4404, "id": "73taa0"}, {"sentiment_compound": -0.4404, "id": "73ujec"}, {"sentiment_compound": 0.0258, "id": "73tu9b"}, {"sentiment_compound": -0.8401, "id": "73vtow"}, {"sentiment_compound": -0.4445, "id": "73spt0"}, {"sentiment_compound": 0.6369, "id": "73vies"}, {"sentiment_compound": -0.3182, "id": "73uxbx"}, {"sentiment_compound": 0.0, "id": "73qqfw"}, {"sentiment_compound": 0.0, "id": "73prj2"}, {"sentiment_compound": 0.3182, "id": "73wbyp"}, {"sentiment_compound": 0.0, "id": "73uj7c"}, {"sentiment_compound": 0.2577, "id": "73sqro"}, {"sentiment_compound": 0.0, "id": "73ucbs"}, {"sentiment_compound": -0.34, "id": "73st2f"}, {"sentiment_compound": -0.793, "id": "73uwqd"}, {"sentiment_compound": -0.6249, "id": "73vbbo"}, {"sentiment_compound": 0.3182, "id": "73t1o4"}, {"sentiment_compound": -0.1926, "id": "73smnn"}, {"sentiment_compound": 0.0, "id": "73tfmc"}, {"sentiment_compound": 0.0, "id": "73uym7"}, {"sentiment_compound": -0.1531, "id": "73rzj6"}, {"sentiment_compound": -0.4767, "id": "73vfoj"}, {"sentiment_compound": -0.3818, "id": "73u1ld"}, {"sentiment_compound": 0.0, "id": "73t9qi"}, {"sentiment_compound": 0.2732, "id": "73sosj"}, {"sentiment_compound": 0.0, "id": "73rrqy"}, {"sentiment_compound": 0.0, "id": "73r9b6"}, {"sentiment_compound": -0.0695, "id": "73ryq1"}, {"sentiment_compound": 0.5267, "id": "73s1tz"}, {"sentiment_compound": -0.2755, "id": "73scqf"}, {"sentiment_compound": 0.5859, "id": "73rdmw"}, {"sentiment_compound": 0.4019, "id": "73sj23"}, {"sentiment_compound": -0.3182, "id": "73qoj4"}, {"sentiment_compound": -0.8126, "id": "73tcih"}, {"sentiment_compound": -0.4404, "id": "73skhg"}, {"sentiment_compound": -0.296, "id": "73tieo"}, {"sentiment_compound": 0.4019, "id": "73sb0n"}, {"sentiment_compound": 0.2023, "id": "73tpgs"}, {"sentiment_compound": 0.5719, "id": "73rcr7"}, {"sentiment_compound": -0.25, "id": "73ufba"}, {"sentiment_compound": 0.0, "id": "73v9my"}, {"sentiment_compound": 0.7184, "id": "73sunv"}, {"sentiment_compound": -0.4939, "id": "73vc4e"}, {"sentiment_compound": 0.25, "id": "73u4sz"}, {"sentiment_compound": -0.128, "id": "73spqa"}, {"sentiment_compound": -0.8271, "id": "73pm9i"}, {"sentiment_compound": 0.7048, "id": "73r5m8"}, {"sentiment_compound": 0.2023, "id": "73pdbw"}, {"sentiment_compound": 0.0, "id": "73sa4k"}, {"sentiment_compound": -0.4215, "id": "73vql3"}, {"sentiment_compound": 0.4019, "id": "73r0uu"}, {"sentiment_compound": -0.2023, "id": "73uxqb"}, {"sentiment_compound": 0.0, "id": "73sgen"}, {"sentiment_compound": 0.0, "id": "73sszb"}, {"sentiment_compound": 0.4019, "id": "73t1st"}, {"sentiment_compound": -0.2023, "id": "73rzs4"}, {"sentiment_compound": -0.6908, "id": "73phqd"}, {"sentiment_compound": -0.4404, "id": "73ua2l"}, {"sentiment_compound": 0.0, "id": "73s9qv"}, {"sentiment_compound": -0.5574, "id": "73us92"}, {"sentiment_compound": 0.0772, "id": "73qdpx"}, {"sentiment_compound": 0.0, "id": "73tyeo"}, {"sentiment_compound": -0.8271, "id": "73p2qk"}, {"sentiment_compound": 0.0, "id": "73q3qj"}, {"sentiment_compound": 0.0, "id": "73u0ax"}, {"sentiment_compound": 0.0, "id": "73t0gm"}, {"sentiment_compound": 0.2732, "id": "73rmne"}, {"sentiment_compound": 0.4019, "id": "73sts3"}, {"sentiment_compound": 0.0, "id": "73q73p"}, {"sentiment_compound": -0.7096, "id": "73upkb"}, {"sentiment_compound": 0.0, "id": "73v3wh"}, {"sentiment_compound": 0.0, "id": "73sw96"}, {"sentiment_compound": 0.0, "id": "73rt64"}, {"sentiment_compound": -0.34, "id": "73szsj"}, {"sentiment_compound": -0.5095, "id": "73vqig"}]